atlas_sdk/__init__.py
atlas_sdk/_version.py
atlas_sdk/deprecation.py
atlas_sdk/exceptions.py
atlas_sdk/instrumentation.py
atlas_sdk/pagination.py
atlas_sdk/py.typed
atlas_sdk/validation.py
atlas_sdk/_internal/__init__.py
atlas_sdk/_internal/http.py
atlas_sdk/_internal/params.py
atlas_sdk/_internal/polling.py
atlas_sdk/clients/__init__.py
atlas_sdk/clients/base.py
atlas_sdk/clients/control_plane.py
atlas_sdk/clients/dispatch.py
atlas_sdk/clients/workflow.py
atlas_sdk/models/__init__.py
atlas_sdk/models/agent_definition.py
atlas_sdk/models/agent_instance.py
atlas_sdk/models/base.py
atlas_sdk/models/deployment.py
atlas_sdk/models/enums.py
atlas_sdk/models/plan.py
atlas_sdk/models/control_plane/__init__.py
atlas_sdk/models/control_plane/agent_class.py
atlas_sdk/models/control_plane/grasp.py
atlas_sdk/models/control_plane/model_provider.py
atlas_sdk/models/control_plane/system_prompt.py
atlas_sdk/models/control_plane/tool.py
atlas_sdk/models/dispatch/__init__.py
atlas_sdk/models/dispatch/schemas.py
atlas_sdk/resources/__init__.py
atlas_sdk/resources/agent_instances.py
atlas_sdk/resources/base.py
atlas_sdk/resources/deployments.py
atlas_sdk/resources/plans.py
atlas_sdk/resources/tasks.py
atlas_sdk/testing/__init__.py
atlas_sdk/testing/factories.py
atlas_sdk/testing/fake_clients.py
atlas_sdk/testing/fixtures.py
atlas_sdk/testing/mock_client.py
ryora_atlas_sdk-0.1.0.dist-info/METADATA
ryora_atlas_sdk-0.1.0.dist-info/WHEEL
ryora_atlas_sdk-0.1.0.dist-info/RECORD
