Metadata-Version: 2.4
Name: ryora-atlas-sdk
Version: 0.1.0
Summary: Official Python SDK for the Atlas Platform
Author-email: Atlas Team <admin@example.com>
License-Expression: MIT
Requires-Python: >=3.13
Requires-Dist: httpx==0.28.1
Requires-Dist: pydantic==2.12.5
Requires-Dist: tenacity==9.1.2
Provides-Extra: dev
Requires-Dist: bandit==1.9.3; extra == 'dev'
Requires-Dist: mypy==1.19.1; extra == 'dev'
Requires-Dist: pip-audit==2.10.0; extra == 'dev'
Requires-Dist: ruff==0.14.14; extra == 'dev'
Provides-Extra: docs
Requires-Dist: mkdocs-material>=9.5.0; extra == 'docs'
Requires-Dist: mkdocs>=1.6.0; extra == 'docs'
Requires-Dist: mkdocstrings[python]>=0.25.0; extra == 'docs'
Provides-Extra: otel
Requires-Dist: opentelemetry-api>=1.20.0; extra == 'otel'
Provides-Extra: test
Requires-Dist: pytest-asyncio==1.3.0; extra == 'test'
Requires-Dist: pytest-cov==7.0.0; extra == 'test'
Requires-Dist: pytest-httpserver==1.1.0; extra == 'test'
Requires-Dist: pytest==9.0.2; extra == 'test'
Requires-Dist: respx==0.22.0; extra == 'test'
